securex/__init__.py
securex-0.0.1.dist-info/METADATA
securex-0.0.1.dist-info/WHEEL
securex-0.0.1.dist-info/top_level.txt
securex-0.0.1.dist-info/RECORD
