Metadata-Version: 2.1
Name: securex
Version: 0.0.1
Summary: Testing something
Home-page: UNKNOWN
Author: Tector Pro
Author-email: UNKNOWN
License: UNKNOWN
Platform: UNKNOWN
